{
  "passionsfrucht": "Obst & Gemüse",
  "getreideriegel": "Süßes & Snacks",
  "glasreiniger": "Haushalt",
  "gartenwerkzeug": "Haushalt",
  "müesli": "Pasta, Reis & Getreide",
  "pinienkerne": "Obst & Gemüse",
  "creme fraiche": "Milchprodukte",
  "hackfleisch": "Fleisch & Fisch",
  "kekse": "Süßes & Snacks",
  "salami": "Fleisch & Fisch",
  "lippenpomade": "Hygiene & Körperpflege",
  "putzmittel": "Haushalt",
  "samen": "Obst & Gemüse",
  "wassermelone": "Obst & Gemüse",
  "schokolade": "Süßes & Snacks",
  "käse": "Milchprodukte",
  "giesskanne": "Haushalt",
  "bratwurst": "Fleisch & Fisch",
  "garnelen": "Fleisch & Fisch",
  "fenchel": "Obst & Gemüse",
  "fruchtsaft": "Getränke",
  "raclette": "Milchprodukte",
  "brokkoli": "Obst & Gemüse",
  "eistee": "Getränke",
  "haarspray": "Hygiene & Körperpflege",
  "pflaumen": "Obst & Gemüse",
  "pommes chips": "Süßes & Snacks",
  "schweinefleisch": "Fleisch & Fisch",
  "backpapier": "Haushalt",
  "brot": "Brot & Backwaren",
  "orangensaft": "Getränke",
  "geschirrsalz": "Haushalt",
  "gipfeli": "Brot & Backwaren",
  "strohhalme": "Haushalt",
  "birnen": "Obst & Gemüse",
  "italian to go": "Sonstiges",
  "eier": "Milchprodukte",
  "makeup entferner": "Hygiene & Körperpflege",
  "kartoffeln": "Obst & Gemüse",
  "rasierklingen": "Hygiene & Körperpflege",
  "kaffee": "Getränke",
  "kohlrabi": "Obst & Gemüse",
  "frischkäse": "Milchprodukte",
  "essiggurken": "Gewürze & Saucen",
  "öl": "Gewürze & Saucen",
  "gelee": "Süßes & Snacks",
  "trauben": "Obst & Gemüse",
  "salz": "Gewürze & Saucen",
  "glühbirne": "Haushalt",
  "balsamico": "Gewürze & Saucen",
  "fisch": "Fleisch & Fisch",
  "geschenk": "Sonstiges",
  "blumen": "Sonstiges",
  "kartoffelstock": "Obst & Gemüse",
  "limonade": "Getränke",
  "schwamm": "Haushalt",
  "ahornsirup": "Gewürze & Saucen",
  "limette": "Obst & Gemüse",
  "aubergine": "Obst & Gemüse",
  "mettigel": "Fleisch & Fisch",
  "nüsse": "Süßes & Snacks",
  "schinken": "Fleisch & Fisch",
  "dip": "Gewürze & Saucen",
  "zucchetti": "Obst & Gemüse",
  "suppe": "Gewürze & Saucen",
  "rum": "Getränke",
  "frühlingszwiebeln": "Obst & Gemüse",
  "spargel": "Obst & Gemüse",
  "sonnencreme": "Hygiene & Körperpflege",
  "gnocchi": "Pasta, Reis & Getreide",
  "handcreme": "Hygiene & Körperpflege",
  "schnittlauch": "Obst & Gemüse",
  "rote bete": "Obst & Gemüse",
  "pelati": "Gewürze & Saucen",
  "fischstäbli": "Tiefkühl",
  "margarine": "Milchprodukte",
  "bbq sauce": "Gewürze & Saucen",
  "zigaretten": "Sonstiges",
  "muscheln": "Fleisch & Fisch",
  "oregano": "Gewürze & Saucen",
  "basmatireis": "Pasta, Reis & Getreide",
  "zahnseide": "Hygiene & Körperpflege",
  "tofu": "Obst & Gemüse",
  "energy drink": "Getränke",
  "peperoni": "Obst & Gemüse",
  "sirup": "Getränke",
  "feigen": "Obst & Gemüse",
  "haselnüsse": "Süßes & Snacks",
  "mehl": "Brot & Backwaren",
  "haferflocken": "Pasta, Reis & Getreide",
  "kokosmilch": "Getränke",
  "apfelmus": "Obst & Gemüse",
  "reis": "Pasta, Reis & Getreide",
  "mascarpone": "Milchprodukte",
  "rasenmäher": "Haushalt",
  "schnitzel": "Fleisch & Fisch",
  "chinese to go": "Sonstiges",
  "grill": "Haushalt",
  "ketchup": "Gewürze & Saucen",
  "lachs": "Fleisch & Fisch",
  "zwiebeln": "Obst & Gemüse",
  "beeren": "Obst & Gemüse",
  "pflaster": "Hygiene & Körperpflege",
  "fischfutter": "Sonstiges",
  "kerzen": "Haushalt",
  "waffeln": "Süßes & Snacks",
  "vanille sauce": "Gewürze & Saucen",
  "kalbfleisch": "Fleisch & Fisch",
  "smoothie": "Getränke",
  "rasierschaum": "Hygiene & Körperpflege",
  "ingwer": "Obst & Gemüse",
  "hüttenkäse": "Milchprodukte",
  "pfirsich": "Obst & Gemüse",
  "sauerrahm": "Milchprodukte",
  "lasagne": "Pasta, Reis & Getreide",
  "pinsel": "Haushalt",
  "hefe": "Brot & Backwaren",
  "kuchen": "Brot & Backwaren",
  "prosecco": "Getränke",
  "tampons": "Hygiene & Körperpflege",
  "thunfisch": "Fleisch & Fisch",
  "zucker": "Brot & Backwaren",
  "chicken wings": "Fleisch & Fisch",
  "pouletbrüstli": "Fleisch & Fisch",
  "blumenkohl": "Obst & Gemüse",
  "speisestärke": "Brot & Backwaren",
  "salat": "Obst & Gemüse",
  "brezeln": "Brot & Backwaren",
  "corn flakes": "Pasta, Reis & Getreide",
  "muffins": "Süßes & Snacks",
  "knoblauch": "Obst & Gemüse",
  "karotten": "Obst & Gemüse",
  "toast": "Brot & Backwaren",
  "waschmittel": "Haushalt",
  "salatsauce": "Gewürze & Saucen",
  "hundefutter": "Sonstiges",
  "soya milch": "Milchprodukte",
  "vanillezucker": "Brot & Backwaren",
  "mundspülung": "Hygiene & Körperpflege",
  "babynahrung": "Sonstiges",
  "windeln": "Sonstiges",
  "kondome": "Hygiene & Körperpflege",
  "couscous": "Pasta, Reis & Getreide",
  "geschirrglanz": "Haushalt",
  "aprikosen": "Obst & Gemüse",
  "himbeeren": "Obst & Gemüse",
  "indian to go": "Sonstiges",
  "oliven": "Gewürze & Saucen",
  "lebkuchen": "Süßes & Snacks",
  "kürbis": "Obst & Gemüse",
  "sportgetränk": "Getränke",
  "tonic water": "Getränke",
  "nektarine": "Obst & Gemüse",
  "penne": "Pasta, Reis & Getreide",
  "shampoo": "Hygiene & Körperpflege",
  "whisky": "Getränke",
  "datteln": "Obst & Gemüse",
  "fondue": "Milchprodukte",
  "kakao": "Getränke",
  "olivenöl": "Gewürze & Saucen",
  "bohnen": "Obst & Gemüse",
  "pizza": "Tiefkühl",
  "kiwi": "Obst & Gemüse",
  "poulet": "Fleisch & Fisch",
  "wasser": "Getränke",
  "milch": "Milchprodukte",
  "kirschen": "Obst & Gemüse",
  "mandeln": "Süßes & Snacks",
  "kichererbsen": "Pasta, Reis & Getreide",
  "kosmetiktücher": "Hygiene & Körperpflege",
  "kaugummi": "Süßes & Snacks",
  "gesichtscreme": "Hygiene & Körperpflege",
  "süsskartoffeln": "Obst & Gemüse",
  "getrocknete tomaten": "Gewürze & Saucen",
  "koriander": "Obst & Gemüse",
  "knäckebrot": "Brot & Backwaren",
  "champignons": "Obst & Gemüse",
  "gemüse gefroren": "Tiefkühl",
  "cola light": "Getränke",
  "orange": "Obst & Gemüse",
  "dessert": "Süßes & Snacks",
  "alufolie": "Haushalt",
  "tortilla chips": "Süßes & Snacks",
  "melone": "Obst & Gemüse",
  "bananen": "Obst & Gemüse",
  "preiselbeer sauce": "Gewürze & Saucen",
  "zahnbürsten": "Hygiene & Körperpflege",
  "zimt": "Gewürze & Saucen",
  "äpfel": "Obst & Gemüse",
  "cola": "Getränke",
  "bouillon": "Gewürze & Saucen",
  "knödel": "Pasta, Reis & Getreide",
  "salbei": "Gewürze & Saucen",
  "radieschen": "Obst & Gemüse",
  "soyasauce": "Gewürze & Saucen",
  "rohschinken": "Fleisch & Fisch",
  "reibkäse": "Milchprodukte",
  "aufschnitt": "Fleisch & Fisch",
  "geschirrtabs": "Haushalt",
  "sonnenschirm": "Sonstiges",
  "mineralwasser": "Getränke",
  "taschentücher": "Hygiene & Körperpflege",
  "feuchttücher": "Hygiene & Körperpflege",
  "erbsen": "Obst & Gemüse",
  "parmesan": "Milchprodukte",
  "nougatcreme": "Süßes & Snacks",
  "speck": "Fleisch & Fisch",
  "avocado": "Obst & Gemüse",
  "quark": "Milchprodukte",
  "paprikapulver": "Gewürze & Saucen",
  "torte": "Süßes & Snacks",
  "abfallsäcke": "Haushalt",
  "essig": "Gewürze & Saucen",
  "dünger": "Haushalt",
  "pilze": "Obst & Gemüse",
  "batterien": "Haushalt",
  "tomatensauce": "Gewürze & Saucen",
  "rucola": "Obst & Gemüse",
  "bier": "Getränke",
  "blumenerde": "Haushalt",
  "rhabarber": "Obst & Gemüse",
  "artischocken": "Obst & Gemüse",
  "rosmarin": "Gewürze & Saucen",
  "salzstangen": "Süßes & Snacks",
  "linsenmittel": "Hygiene & Körperpflege",
  "nagellackentferner": "Hygiene & Körperpflege",
  "bodylotion": "Hygiene & Körperpflege",
  "apfelsaft": "Getränke",
  "pudding": "Süßes & Snacks",
  "vitamine": "Hygiene & Körperpflege",
  "thai to go": "Sonstiges",
  "guetzli": "Süßes & Snacks",
  "binden": "Hygiene & Körperpflege",
  "tomatenmark": "Gewürze & Saucen",
  "gurke": "Obst & Gemüse",
  "holzkohle": "Haushalt",
  "basilikum": "Gewürze & Saucen",
  "joghurt": "Milchprodukte",
  "pop corn": "Süßes & Snacks",
  "weichspüler": "Haushalt",
  "butter": "Milchprodukte",
  "dörrobst": "Obst & Gemüse",
  "rotwein": "Getränke",
  "frankfurter": "Fleisch & Fisch",
  "schnaps": "Getränke",
  "tomaten": "Obst & Gemüse",
  "ricotta": "Milchprodukte",
  "watterondellen": "Hygiene & Körperpflege",
  "erdbeeren": "Obst & Gemüse",
  "vogelfutter": "Sonstiges",
  "thymian": "Gewürze & Saucen",
  "katzensnack": "Sonstiges",
  "puderzucker": "Brot & Backwaren",
  "kräuterbutter": "Milchprodukte",
  "kaki": "Obst & Gemüse",
  "insektenschutzmittel": "Haushalt",
  "erdnüsse": "Süßes & Snacks",
  "pfefferkörner": "Gewürze & Saucen",
  "schrauben": "Haushalt",
  "sardellen": "Fleisch & Fisch",
  "rindfleisch": "Fleisch & Fisch",
  "conditioner": "Hygiene & Körperpflege",
  "pizzateig": "Tiefkühl",
  "blauschimmelkäse": "Milchprodukte",
  "zitrone": "Obst & Gemüse",
  "nägel": "Haushalt",
  "peperoncini": "Obst & Gemüse",
  "senf": "Gewürze & Saucen",
  "brötchen": "Brot & Backwaren",
  "baumnüsse": "Süßes & Snacks",
  "nudeln": "Pasta, Reis & Getreide",
  "wurst": "Fleisch & Fisch",
  "griess": "Pasta, Reis & Getreide",
  "mandarinen": "Obst & Gemüse",
  "weisswein": "Getränke",
  "blätterteig": "Tiefkühl",
  "zahnstocher": "Haushalt",
  "cherrytomaten": "Obst & Gemüse",
  "pfefferminze": "Gewürze & Saucen",
  "katzenstreu": "Sonstiges",
  "kohl": "Obst & Gemüse",
  "brombeeren": "Obst & Gemüse",
  "feta": "Milchprodukte",
  "gin": "Getränke",
  "vodka": "Getränke",
  "honig": "Gewürze & Saucen",
  "wc-papier": "Haushalt",
  "paniermehl": "Brot & Backwaren",
  "rahm": "Milchprodukte",
  "mayonnaise": "Gewürze & Saucen",
  "spülmittel": "Haushalt",
  "sellerie": "Obst & Gemüse",
  "lauch": "Obst & Gemüse",
  "light limonade": "Getränke",
  "rindsgeschnetzeltes": "Fleisch & Fisch",
  "wc-reiniger": "Haushalt",
  "baguette": "Brot & Backwaren",
  "konfitüre": "Gewürze & Saucen",
  "schmerzmittel": "Hygiene & Körperpflege",
  "badreiniger": "Haushalt",
  "heidelbeeren": "Obst & Gemüse",
  "mango": "Obst & Gemüse",
  "mozzarella": "Milchprodukte",
  "ananas": "Obst & Gemüse",
  "propangas": "Haushalt",
  "streichhölzer": "Haushalt",
  "pasta sauce": "Gewürze & Saucen",
  "bratensauce": "Gewürze & Saucen",
  "lamm": "Fleisch & Fisch",
  "frischhaltefolie": "Haushalt",
  "zahnpasta": "Hygiene & Körperpflege",
  "spaghetti": "Pasta, Reis & Getreide",
  "haargel": "Hygiene & Körperpflege",
  "snacks": "Süßes & Snacks",
  "petersilie": "Gewürze & Saucen",
  "grapefruit": "Obst & Gemüse",
  "servietten": "Haushalt",
  "töpfe": "Haushalt",
  "linsen": "Pasta, Reis & Getreide",
  "lattich": "Obst & Gemüse",
  "duschmittel": "Hygiene & Körperpflege",
  "gorgonzola": "Milchprodukte",
  "spinat": "Obst & Gemüse",
  "steak": "Fleisch & Fisch",
  "hundesnack": "Sonstiges",
  "backpulver": "Brot & Backwaren",
  "risottoreis": "Pasta, Reis & Getreide",
  "rasierer": "Hygiene & Körperpflege",
  "pommes frites": "Tiefkühl",
  "deo": "Hygiene & Körperpflege",
  "pflanzen": "Haushalt",
  "katzenfutter": "Sonstiges",
  "geschenkpapier": "Sonstiges",
  "champagner": "Getränke",
  "nagellack": "Hygiene & Körperpflege",
  "tee": "Getränke",
  "wattestäbchen": "Hygiene & Körperpflege",
  "kräuter": "Gewürze & Saucen",
  "seife": "Hygiene & Körperpflege",
  "glacé": "Süßes & Snacks",
  "mais": "Obst & Gemüse",
  "haushaltspapier": "Haushalt",
  "süssigkeiten": "Süßes & Snacks",
  "burrata": "Milchprodukte",
  "mandelmus": "Süßes & Snacks",
  "silberzwiebeln": "Gewürze & Saucen",
  "müsli": "Pasta, Reis & Getreide",
  "lippenpflege": "Hygiene & Körperpflege",
  "sämereien": "Obst & Gemüse",
  "raclettekäse": "Milchprodukte",
  "chips": "Süßes & Snacks",
  "croissant": "Brot & Backwaren",
  "italienisches essen": "Sonstiges",
  "kartoffelpüree": "Obst & Gemüse",
  "mett für igel": "Fleisch & Fisch",
  "zucchini": "Obst & Gemüse",
  "dosentomaten": "Gewürze & Saucen",
  "fischstäbchen": "Tiefkühl",
  "paprika": "Obst & Gemüse",
  "chinesisches essen": "Sonstiges",
  "sekt": "Getränke",
  "hähnchenbrust": "Fleisch & Fisch",
  "sojamilch": "Milchprodukte",
  "klarspüler": "Haushalt",
  "indisches essen": "Sonstiges",
  "fonduekäse": "Milchprodukte",
  "hähnchen": "Fleisch & Fisch",
  "süßkartoffeln": "Obst & Gemüse",
  "brühe": "Gewürze & Saucen",
  "sojasauce": "Gewürze & Saucen",
  "müllsäcke": "Haushalt",
  "thai essen": "Sonstiges",
  "plätzchen": "Süßes & Snacks",
  "wattepads": "Hygiene & Körperpflege",
  "haarspülung": "Hygiene & Körperpflege",
  "chili": "Gewürze & Saucen",
  "walnüsse": "Süßes & Snacks",
  "grieß": "Pasta, Reis & Getreide",
  "wodka": "Getränke",
  "toilettenpapier": "Haushalt",
  "semmelbrösel": "Brot & Backwaren",
  "sahne": "Milchprodukte",
  "rindergeschnetzeltes": "Fleisch & Fisch",
  "toilettenreiniger": "Haushalt",
  "marmelade": "Gewürze & Saucen",
  "duschgel": "Hygiene & Körperpflege",
  "eis": "Süßes & Snacks",
  "küchenrolle": "Haushalt",
  "aperol": "Getränke",
  "aperol spritz": "Getränke",
  "spritz": "Getränke",
  "bulgur": "Pasta, Reis & Getreide",
  "emmentaler": "Milchprodukte",
  "magerquark": "Milchprodukte",
  "quinoa": "Pasta, Reis & Getreide",
  "räucherlachs": "Fleisch & Fisch",
  "tortilla wraps": "Brot & Backwaren",
  "wraps": "Brot & Backwaren",
  "tortillas": "Brot & Backwaren",
  "glasnudeln": "Pasta, Reis & Getreide",
  "cellophane nudeln": "Pasta, Reis & Getreide",
  "grünkohl": "Obst & Gemüse",
  "kale": "Obst & Gemüse",
  "kokosnuss": "Obst & Gemüse",
  "kokos": "Obst & Gemüse",
  "lychee": "Obst & Gemüse",
  "litchi": "Obst & Gemüse",
  "mangold": "Obst & Gemüse",
  "pak choi": "Obst & Gemüse",
  "bok choy": "Obst & Gemüse",
  "pastinaken": "Obst & Gemüse",
  "reisnudeln": "Pasta, Reis & Getreide",
  "rice noodles": "Pasta, Reis & Getreide",
  "rettich": "Obst & Gemüse",
  "daikon": "Obst & Gemüse",
  "stroh 80": "Getränke",
  "stroh rum": "Getränke",
  "topinambur": "Obst & Gemüse",
  "jerusalem artichoke": "Obst & Gemüse"
}
